cottonformation/__init__.py
cottonformation/_version.py
cottonformation/code/__init__.py
cottonformation/code/spec.py
cottonformation/code/spec_file/__init__.py
cottonformation/code/spec_file/downloader.py
cottonformation/code/spec_file/inspect.py
cottonformation/code/spec_file/paths.py
cottonformation/core/__init__.py
cottonformation/core/config.py
cottonformation/core/console.py
cottonformation/core/constant.py
cottonformation/core/env.py
cottonformation/core/exc.py
cottonformation/core/model.py
cottonformation/core/regex.py
cottonformation/core/stack.py
cottonformation/core/tagging.py
cottonformation/core/template.py
cottonformation/core/helpers/__init__.py
cottonformation/core/helpers/_iam_aws_managed_policy.py
cottonformation/core/helpers/_iam_aws_service_principal.py
cottonformation/core/helpers/awslambda.py
cottonformation/core/helpers/iam.py
cottonformation/docs/__init__.py
cottonformation/examples/__init__.py
cottonformation/examples/s1_quick_start/__init__.py
cottonformation/examples/s1_quick_start/e01_basic.py
cottonformation/examples/s1_quick_start/e02_tagging.py
cottonformation/examples/s1_quick_start/e03_nested.py
cottonformation/examples/s1_quick_start/e04_intrinsic_function.py
cottonformation/examples/s1_quick_start/e04_intrinsic_function_alt.py
cottonformation/examples/s1_quick_start/e05_condition.py
cottonformation/examples/s1_quick_start/e05_condition_alt.py
cottonformation/examples/s2_best_practice/__init__.py
cottonformation/examples/s2_best_practice/e01_old_styled_parameter.py
cottonformation/examples/s2_best_practice/e02_ctf_styled_parameter.py
cottonformation/examples/s2_best_practice/e03_res_group_1.py
cottonformation/examples/s2_best_practice/e03_res_group_2.py
cottonformation/examples/s2_best_practice/e03_res_group_3.py
cottonformation/examples/s2_best_practice/e03_res_group_4.py
cottonformation/examples/s2_best_practice/e03_res_group_5.py
cottonformation/res/__init__.py
cottonformation/res/_imp.py
cottonformation/res/accessanalyzer.py
cottonformation-1.1.2.dist-info/AUTHORS.rst
cottonformation-1.1.2.dist-info/LICENSE.txt
cottonformation-1.1.2.dist-info/METADATA
cottonformation-1.1.2.dist-info/WHEEL
cottonformation-1.1.2.dist-info/top_level.txt
cottonformation-1.1.2.dist-info/RECORD
