Metadata-Version: 2.1
Name: cottonformation
Version: 1.1.2
Summary: Modern CloudFormation Python tool with Type hint, Parameter hint, Doc hint + Auto Validation in Real Objective Programming Style.
Home-page: https://github.com/MacHu-GWU/cottonformation-project
Download-URL: https://pypi.python.org/pypi/cottonformation/1.1.2#downloads
Author: Sanhe Hu
Author-email: husanhe@gmail.com
Maintainer: Unknown
License: BSD License
Platform: Windows
Platform: MacOS
Platform: Unix
Classifier: Development Status :: 4 - Beta
Classifier: Intended Audience :: Developers
Classifier: License :: OSI Approved :: BSD License
Classifier: Natural Language :: English
Classifier: Operating System :: Microsoft :: Windows
Classifier: Operating System :: MacOS
Classifier: Operating System :: Unix
Classifier: Programming Language :: Python
Classifier: Programming Language :: Python :: 3 :: Only
Classifier: Programming Language :: Python :: 3.6
Classifier: Programming Language :: Python :: 3.7
Classifier: Programming Language :: Python :: 3.8
Classifier: Programming Language :: Python :: 3.9
Classifier: Programming Language :: Python :: 3.10
License-File: LICENSE.txt
License-File: AUTHORS.rst
Requires-Dist: attrs
Requires-Dist: boto-session-manager (>=1.3.1)
Requires-Dist: aws-cloudformation (>=1.3.2)
Requires-Dist: toposort (>=1.6)
Requires-Dist: cfn-flip (>=1.0.0)
Provides-Extra: docs
Requires-Dist: sphinx (==4.3.0) ; extra == 'docs'
Requires-Dist: sphinx-inline-tabs (==2021.8.17b10) ; extra == 'docs'
Requires-Dist: sphinx-jinja (==1.1.1) ; extra == 'docs'
Requires-Dist: sphinx-copybutton (==0.4.0) ; extra == 'docs'
Requires-Dist: rstobj (==0.0.7) ; extra == 'docs'
Requires-Dist: docfly (==1.0.2) ; extra == 'docs'
Requires-Dist: furo (==2021.8.31) ; extra == 'docs'
Provides-Extra: tests
Requires-Dist: pytest ; extra == 'tests'
Requires-Dist: pytest-cov ; extra == 'tests'
Requires-Dist: twine (>=1.13.0) ; extra == 'tests'
Requires-Dist: wheel (>=0.33.1) ; extra == 'tests'
Requires-Dist: pathlib-mate ; extra == 'tests'
Requires-Dist: requests ; extra == 'tests'
Requires-Dist: jinja2 ; extra == 'tests'
Requires-Dist: boto3 ; extra == 'tests'
Requires-Dist: SQLAlchemy (==1.4.20) ; extra == 'tests'
Requires-Dist: psycopg2-binary (==2.9.5) ; extra == 'tests'
Requires-Dist: pysecret (==0.0.8) ; extra == 'tests'
